data_logging/__init__.py
data_logging/annotators.py
data_logging/datetime_helpers.py
data_logging/example.py
data_logging/formatters.py
data_logging/handlers.py
data_logging/subsix.py
data_logging/utils.py
data_logging-1.2.0.dist-info/DESCRIPTION.rst
data_logging-1.2.0.dist-info/METADATA
data_logging-1.2.0.dist-info/RECORD
data_logging-1.2.0.dist-info/WHEEL
data_logging-1.2.0.dist-info/metadata.json
data_logging-1.2.0.dist-info/top_level.txt
