Metadata-Version: 2.0
Name: data-logging
Version: 1.2.0
Summary: Common library for logging from python in machine-readable form
Home-page: UNKNOWN
Author: HoverHell
Author-email: hoverhell@gmail.com
License: UNKNOWN
Platform: UNKNOWN
